elastic_enterprise_search/__init__.py
elastic_enterprise_search/_serializer.py
elastic_enterprise_search/_utils.py
elastic_enterprise_search/_version.py
elastic_enterprise_search/exceptions.py
elastic_enterprise_search/_async/__init__.py
elastic_enterprise_search/_async/client/__init__.py
elastic_enterprise_search/_async/client/_base.py
elastic_enterprise_search/_async/client/app_search.py
elastic_enterprise_search/_async/client/enterprise_search.py
elastic_enterprise_search/_async/client/workplace_search.py
elastic_enterprise_search/_sync/__init__.py
elastic_enterprise_search/_sync/client/__init__.py
elastic_enterprise_search/_sync/client/_base.py
elastic_enterprise_search/_sync/client/app_search.py
elastic_enterprise_search/_sync/client/enterprise_search.py
elastic_enterprise_search/_sync/client/workplace_search.py
elastic_enterprise_search-8.18.0.dist-info/licenses/LICENSE
elastic_enterprise_search-8.18.0.dist-info/METADATA
elastic_enterprise_search-8.18.0.dist-info/WHEEL
elastic_enterprise_search-8.18.0.dist-info/top_level.txt
elastic_enterprise_search-8.18.0.dist-info/RECORD
